{
    "meta": {
        "track": "Narromine",
        "date": "2026-04-26",
        "track_condition": "Good 4"
    },
    "races": [
        {
            "number": 1,
            "distance": "6 1/2 f",
            "surface": "Turf",
            "confidence_level": "Medium",
            "selections": [
                {
                    "number": "1",
                    "barrier": "8",
                    "name": "Castro (NZ)",
                    "rating": 100,
                    "reason": "Consistent form with a 3rd at Mudgee and 5th at Orange. Strong speed figures make him the obvious threat."
                },
                {
                    "number": "4",
                    "barrier": "3",
                    "name": "Pinero",
                    "rating": 96,
                    "reason": "Improving form, coming off a solid 2nd at Tamworth. Drawn well to feature."
                },
                {
                    "number": "6",
                    "barrier": "4",
                    "name": "Bravalatante",
                    "rating": 92,
                    "reason": "Boxed on steadily for 4th at Dubbo last start. Has minor claims."
                },
                {
                    "number": "2",
                    "barrier": "7",
                    "name": "Smart Scud",
                    "rating": 88,
                    "reason": "Trained by Tier 1 stable, open to improvement after debut 7th at Scone."
                }
            ],
            "danger_horse": {
                "number": "8",
                "barrier": "2",
                "name": "Millicent Daisy",
                "rating": 85,
                "reason": "Led and faded last start but open to improvement."
            },
            "exotic_strategy": {
                "strategy": "Exacta Box 1, 4, Trifecta 1, 4 / 1, 2, 4, 6 / 1, 2, 4, 6, 8"
            }
        },
        {
            "number": 2,
            "distance": "5 1/2 f",
            "surface": "Turf",
            "confidence_level": "High",
            "selections": [
                {
                    "number": "1",
                    "barrier": "6",
                    "name": "Erion",
                    "rating": 102,
                    "reason": "Racing well with consecutive 2nd place finishes. Edged out late last start, ready to win."
                },
                {
                    "number": "5",
                    "barrier": "3",
                    "name": "Territory Style",
                    "rating": 98,
                    "reason": "Made good headway for 2nd at Wellington. Perfectly placed over the extra distance."
                },
                {
                    "number": "3",
                    "barrier": "5",
                    "name": "Northern Exposure",
                    "rating": 94,
                    "reason": "Resuming from a break. Has placed first-up previously and faces a field lacking depth."
                },
                {
                    "number": "8",
                    "barrier": "1",
                    "name": "Moon Dart",
                    "rating": 90,
                    "reason": "Boxed on steadily for 5th at Wellington. Blinkers may sharpen him up."
                }
            ],
            "danger_horse": {
                "number": "7",
                "barrier": "4",
                "name": "Corky",
                "rating": 88,
                "reason": "Finished 4th on debut at Wellington. Open to natural improvement."
            },
            "exotic_strategy": {
                "strategy": "Exacta Box 1, 5, Trifecta 1, 5 / 1, 3, 5 / 1, 3, 5, 7, 8"
            }
        },
        {
            "number": 3,
            "distance": "5 1/2 f",
            "surface": "Turf",
            "confidence_level": "Medium",
            "selections": [
                {
                    "number": "11",
                    "barrier": "3",
                    "name": "Rubelin",
                    "rating": 98,
                    "reason": "Promising 4th on debut at Scone. Fitter now and should appreciate the drop in class."
                },
                {
                    "number": "3",
                    "barrier": "8",
                    "name": "Finest Art",
                    "rating": 96,
                    "reason": "Made ground from midfield for 3rd at Wellington. Consistent and a major player."
                },
                {
                    "number": "1",
                    "barrier": "11",
                    "name": "All Saints",
                    "rating": 93,
                    "reason": "Finished 4th at Wellington last start. Tricky gate but among the top chances."
                },
                {
                    "number": "6",
                    "barrier": "1",
                    "name": "Sibeila",
                    "rating": 90,
                    "reason": "Resuming after a year break. Trial winner recently, watch betting market."
                }
            ],
            "danger_horse": {
                "number": "2",
                "barrier": "7",
                "name": "Bindaree Lass",
                "rating": 88,
                "reason": "Resuming. Showed ability last prep, capable of a solid performance."
            },
            "exotic_strategy": {
                "strategy": "Exacta Box 3, 11, Trifecta 3, 11 / 1, 3, 11 / 1, 2, 3, 6, 11"
            }
        },
        {
            "number": 4,
            "distance": "1 m",
            "surface": "Turf",
            "confidence_level": "High",
            "selections": [
                {
                    "number": "3",
                    "barrier": "8",
                    "name": "Strassman",
                    "rating": 102,
                    "reason": "Broke through for a win at Wellington last start. Found form and expected to feature again."
                },
                {
                    "number": "4",
                    "barrier": "5",
                    "name": "The Bentley",
                    "rating": 98,
                    "reason": "Racing well with a 2nd at Grenfell and 4th at Wellington. Sound each-way hope."
                },
                {
                    "number": "7",
                    "barrier": "6",
                    "name": "Litlfela",
                    "rating": 95,
                    "reason": "Finished 4th at Wellington recently. Very fit and ready to show his best."
                },
                {
                    "number": "1",
                    "barrier": "3",
                    "name": "Himeros",
                    "rating": 92,
                    "reason": "Faded to 5th at Orange last start but capable of better in this grade."
                }
            ],
            "danger_horse": {
                "number": "10",
                "barrier": "7",
                "name": "Indie Mae",
                "rating": 90,
                "reason": "Fitter now and can improve without surprising."
            },
            "exotic_strategy": {
                "strategy": "Exacta Box 3, 4, Trifecta 3, 4 / 3, 4, 7 / 1, 3, 4, 7, 10"
            }
        },
        {
            "number": 5,
            "distance": "6 1/2 f",
            "surface": "Turf",
            "confidence_level": "High",
            "selections": [
                {
                    "number": "1",
                    "barrier": "6",
                    "name": "Micro Mikki",
                    "rating": 115,
                    "reason": "Massive class drop from Randwick Highway and Country Championships. Dominant rating advantage."
                },
                {
                    "number": "3",
                    "barrier": "1",
                    "name": "Red Beryl",
                    "rating": 100,
                    "reason": "Won at Warren recently and drops back from tougher grades. Major player."
                },
                {
                    "number": "8",
                    "barrier": "3",
                    "name": "Turgenev",
                    "rating": 96,
                    "reason": "Ran on strongly for 2nd at Orange last start. Close up recently and commands respect."
                },
                {
                    "number": "7",
                    "barrier": "2",
                    "name": "Stockholm",
                    "rating": 94,
                    "reason": "Won at Dubbo two starts back. Can bounce back from a moderate effort at Mudgee."
                }
            ],
            "danger_horse": {
                "number": "4",
                "barrier": "4",
                "name": "Sebilla",
                "rating": 92,
                "reason": "Resuming. Has class but might need the run. Watch for late market support."
            },
            "exotic_strategy": {
                "strategy": "Win Bet #1, Exacta 1 / 3, 7, 8, Trifecta 1 / 3, 7, 8 / 3, 4, 7, 8"
            }
        },
        {
            "number": 6,
            "distance": "5 1/2 f",
            "surface": "Turf",
            "confidence_level": "Medium",
            "selections": [
                {
                    "number": "12",
                    "barrier": "9",
                    "name": "Chappolicious",
                    "rating": 98,
                    "reason": "Gave a good sight when 3rd at Wellington. Strong winning chance from a favorable draw."
                },
                {
                    "number": "11",
                    "barrier": "6",
                    "name": "Invincible Salex",
                    "rating": 96,
                    "reason": "Fitter second-up. Won at Muswellbrook last prep and is an excellent winning chance."
                },
                {
                    "number": "1",
                    "barrier": "2",
                    "name": "Line Of Law",
                    "rating": 94,
                    "reason": "Won at Tullibigeal two starts back. Inside draw is a big advantage here."
                },
                {
                    "number": "7",
                    "barrier": "8",
                    "name": "Sidenay",
                    "rating": 92,
                    "reason": "Finished 2nd at Lightning Ridge last start. Capable of another forward showing."
                }
            ],
            "danger_horse": {
                "number": "5",
                "barrier": "1",
                "name": "Race To Arms",
                "rating": 90,
                "reason": "Won at Coonamble last prep. Excellent winning chance if he brings his best."
            },
            "exotic_strategy": {
                "strategy": "Exacta Box 11, 12, Trifecta 11, 12 / 1, 11, 12 / 1, 5, 7, 11, 12"
            }
        },
        {
            "number": 7,
            "distance": "6 1/2 f",
            "surface": "Turf",
            "confidence_level": "Low",
            "selections": [
                {
                    "number": "2",
                    "barrier": "12",
                    "name": "Charlie Magic",
                    "rating": 96,
                    "reason": "Solid 3rd at Dubbo last start. Will need some improvement but right in this."
                },
                {
                    "number": "7",
                    "barrier": "4",
                    "name": "St Roy",
                    "rating": 95,
                    "reason": "Won at Lightning Ridge two starts back. Well placed and a terrific chance to return to form."
                },
                {
                    "number": "5",
                    "barrier": "2",
                    "name": "Friskee Frog",
                    "rating": 94,
                    "reason": "Resuming favorite. Won at Warren last prep and drawn well to feature."
                },
                {
                    "number": "3",
                    "barrier": "11",
                    "name": "Eilrahc",
                    "rating": 92,
                    "reason": "Finished 5th at Orange last start. Rates highly on best form and should be in the mix."
                }
            ],
            "danger_horse": {
                "number": "8",
                "barrier": "15",
                "name": "Cheap Shot",
                "rating": 90,
                "reason": "Consistent form, 3rd at Goulburn last start. Rates highly and worth including."
            },
            "exotic_strategy": {
                "strategy": "Exacta Box 2, 7, Trifecta 2, 7 / 2, 5, 7 / 2, 3, 5, 7, 8"
            }
        }
    ]
}