{
    "meta": {
        "track": "Santa_Anita",
        "date": "2026-04-25",
        "track_condition": "Fast/Firm"
    },
    "races": [
        {
            "number": 1,
            "distance": "1 Mile",
            "surface": "Turf",
            "confidence_level": "High",
            "selections": [
                {
                    "number": "7",
                    "barrier": "7",
                    "name": "Moonlit Sonata",
                    "rating": 105,
                    "reason": "Top speed figures in the field (118) and drops into a softer SOC spot. Form cycle indicates a peak effort."
                },
                {
                    "number": "5",
                    "barrier": "5",
                    "name": "Kokosan",
                    "rating": 103,
                    "reason": "Consistent presser with a 115 speed rating. Fresu in the irons adds confidence for a stalking trip."
                },
                {
                    "number": "3",
                    "barrier": "3",
                    "name": "Rostovsky",
                    "rating": 100,
                    "reason": "Solid class rating of 107 and fits well in this pace scenario. Should be closing late."
                },
                {
                    "number": "2",
                    "barrier": "2",
                    "name": "Sneaking Candy",
                    "rating": 95,
                    "reason": "Early speed threat who could get brave if left alone on the lead, though turf penalizes pure 'E' types slightly."
                }
            ],
            "danger_horse": {
                "number": "1",
                "barrier": "1",
                "name": "Sand Bagger",
                "rating": 93,
                "reason": "Rail draw and Tyler Baze could work out a ground-saving trip at a price."
            },
            "exotic_strategy": "Win Bet #7, Exacta Box 5-7, Trifecta 5,7 / 3,5,7 / 1,2,3,5,7"
        },
        {
            "number": 2,
            "distance": "6 Furlongs",
            "surface": "Dirt",
            "confidence_level": "High",
            "selections": [
                {
                    "number": "1",
                    "barrier": "1",
                    "name": "Sendit Mo",
                    "rating": 102,
                    "reason": "Standout on class and speed (107). Fresu rides for Papaprodromou. The clear horse to beat."
                },
                {
                    "number": "2",
                    "barrier": "2",
                    "name": "Rollinwithpolan",
                    "rating": 98,
                    "reason": "Speed rating of 105 makes him the logical alternative if the favorite falters."
                },
                {
                    "number": "4",
                    "barrier": "4",
                    "name": "Straight Buzzin",
                    "rating": 95,
                    "reason": "Hernandez takes the mount; possesses enough tactical speed to secure a good position."
                },
                {
                    "number": "5",
                    "barrier": "5",
                    "name": "Desert Kat",
                    "rating": 90,
                    "reason": "Outside draw is favorable, but needs to improve on a 95 speed rating to challenge the top pair."
                }
            ],
            "danger_horse": null,
            "exotic_strategy": "Exacta 1 / 2,4, Trifecta 1 / 2,4 / 2,4,5"
        },
        {
            "number": 3,
            "distance": "6 Furlongs",
            "surface": "Dirt",
            "confidence_level": "Medium",
            "selections": [
                {
                    "number": "4",
                    "barrier": "4",
                    "name": "Dreaming On",
                    "rating": 105,
                    "reason": "Strong 112 speed rating and 107 class. Kimura rides for Yakteen. Looks primed for a breakthrough."
                },
                {
                    "number": "3",
                    "barrier": "3",
                    "name": "Woodson",
                    "rating": 100,
                    "reason": "Jaramillo aboard for Eurton. 106 speed rating puts him right in the mix."
                },
                {
                    "number": "6",
                    "barrier": "6",
                    "name": "Pacer",
                    "rating": 92,
                    "reason": "First-time starter for Sadler with Fresu riding. Outside post is a plus for a debut runner."
                },
                {
                    "number": "1",
                    "barrier": "1",
                    "name": "Kore Kinetic",
                    "rating": 88,
                    "reason": "First start since being gelded. Could show improvement at a price."
                }
            ],
            "danger_horse": {
                "number": "2",
                "barrier": "2",
                "name": "Rags Over Riches",
                "rating": 85,
                "reason": "Baltas trainee with Ayuso riding; dangerous connections."
            },
            "exotic_strategy": "Win Bet #4, Exacta Box 3-4, Trifecta 3,4 / 3,4,6 / 1,2,3,4,6"
        },
        {
            "number": 4,
            "distance": "1 Mile",
            "surface": "Turf",
            "confidence_level": "Medium",
            "selections": [
                {
                    "number": "3",
                    "barrier": "3",
                    "name": "Gallatin",
                    "rating": 102,
                    "reason": "Speed rating of 112 and class of 101. Peter Miller trainee with Kimura up is a strong combination."
                },
                {
                    "number": "7",
                    "barrier": "7",
                    "name": "Savage Warden",
                    "rating": 99,
                    "reason": "D'Amato trainee with Fresu. 111 speed rating shows he belongs with these."
                },
                {
                    "number": "1",
                    "barrier": "1",
                    "name": "Fumano's Magic",
                    "rating": 96,
                    "reason": "Rail draw and Tyler Baze. 107 speed rating makes him a contender for the exotics."
                },
                {
                    "number": "4",
                    "barrier": "4",
                    "name": "Prime Artist (fr)",
                    "rating": 94,
                    "reason": "European import with Ayuso riding. Class rating of 100 suggests upside."
                }
            ],
            "danger_horse": {
                "number": "8",
                "barrier": "8",
                "name": "Map Me Sexy",
                "rating": 92,
                "reason": "O'Neill trainee with Jaramillo. Outside post but has tactical speed."
            },
            "exotic_strategy": "Win Bet #3, Exacta Box 3-7, Trifecta 3,7 / 1,3,4,7 / 1,3,4,7,8"
        },
        {
            "number": 5,
            "distance": "6 1/2 Furlongs",
            "surface": "Dirt",
            "confidence_level": "High",
            "selections": [
                {
                    "number": "2",
                    "barrier": "2",
                    "name": "Red Flag",
                    "rating": 106,
                    "reason": "Classy veteran with a 113 speed rating and 108 class. Drops into a very winnable spot."
                },
                {
                    "number": "8",
                    "barrier": "8",
                    "name": "Shady Tiger",
                    "rating": 104,
                    "reason": "D'Amato trainee drawn perfectly outside. 113 speed rating matches the top pick."
                },
                {
                    "number": "7",
                    "barrier": "7",
                    "name": "Whiskyginandbrandy",
                    "rating": 98,
                    "reason": "Fresu rides for Knapp. 104 speed rating and consistent form make him a major player."
                },
                {
                    "number": "4",
                    "barrier": "4",
                    "name": "Mega Moon",
                    "rating": 95,
                    "reason": "Hernandez up for Ellis. 113 speed rating shows high ceiling if he fires his best shot."
                }
            ],
            "danger_horse": null,
            "exotic_strategy": "Exacta Box 2-8, Trifecta 2,8 / 2,4,7,8 / 2,4,7,8"
        },
        {
            "number": 6,
            "distance": "Abt. 6 1/2 Furlongs",
            "surface": "Turf",
            "confidence_level": "High",
            "selections": [
                {
                    "number": "3",
                    "barrier": "3",
                    "name": "On The Whim",
                    "rating": 108,
                    "reason": "Massive 128 speed rating and 111 class. Looks like a standout on paper."
                },
                {
                    "number": "6",
                    "barrier": "6",
                    "name": "Lonesome Stew",
                    "rating": 105,
                    "reason": "Fresu rides for Glatt. 114 speed rating and 106 class. The main danger to the top pick."
                },
                {
                    "number": "2",
                    "barrier": "2",
                    "name": "Sir Rocket",
                    "rating": 102,
                    "reason": "Mike Smith rides this veteran with a 121 speed rating. Dangerous if he gets loose."
                },
                {
                    "number": "5",
                    "barrier": "5",
                    "name": "Bro Bro",
                    "rating": 99,
                    "reason": "Geroux rides for O'Neill. 115 speed rating puts him in the exotic mix."
                }
            ],
            "danger_horse": {
                "number": "1",
                "barrier": "1",
                "name": "Re Armed Jon",
                "rating": 95,
                "reason": "Rail draw and 120 speed rating. Could sneak into the trifecta at a price."
            },
            "exotic_strategy": "Win Bet #3, Exacta 3 / 2,6, Trifecta 3 / 2,6 / 1,2,5,6"
        },
        {
            "number": 7,
            "distance": "1 Mile",
            "surface": "Dirt",
            "confidence_level": "Low",
            "selections": [
                {
                    "number": "7",
                    "barrier": "7",
                    "name": "Lil's Coffee",
                    "rating": 98,
                    "reason": "O'Neill trainee with Jaramillo. Class rating of 101 is superior in this weak field."
                },
                {
                    "number": "5",
                    "barrier": "5",
                    "name": "Exington",
                    "rating": 95,
                    "reason": "Fresu rides for Miyadi. 107 speed rating shows she can run with these."
                },
                {
                    "number": "1",
                    "barrier": "1",
                    "name": "A Fleet Ride",
                    "rating": 92,
                    "reason": "Rail draw and Ayuso. 100 speed rating makes her a logical contender."
                },
                {
                    "number": "4",
                    "barrier": "4",
                    "name": "Makenarita",
                    "rating": 89,
                    "reason": "Kimura rides. 102 speed rating gives her a chance to hit the board."
                }
            ],
            "danger_horse": {
                "number": "6",
                "barrier": "6",
                "name": "Can'tdealwithit",
                "rating": 85,
                "reason": "Drops in class and could wake up in this spot."
            },
            "exotic_strategy": "Exacta Box 5-7, Trifecta 5,7 / 1,4,5,7 / 1,4,5,6,7"
        },
        {
            "number": 8,
            "distance": "1 Mile",
            "surface": "Turf",
            "confidence_level": "Medium",
            "selections": [
                {
                    "number": "3",
                    "barrier": "3",
                    "name": "Uncle Chilly",
                    "rating": 104,
                    "reason": "Ayuso rides for Mullins. 116 speed rating and 105 class makes him the one to beat."
                },
                {
                    "number": "5",
                    "barrier": "5",
                    "name": "Mici's Express",
                    "rating": 100,
                    "reason": "Jaramillo rides for O'Neill. 107 speed rating and consistent form."
                },
                {
                    "number": "9",
                    "barrier": "9",
                    "name": "Majestic Palisades",
                    "rating": 96,
                    "reason": "Hernandez rides. 105 speed rating and should get a good stalking trip."
                },
                {
                    "number": "7",
                    "barrier": "7",
                    "name": "Crypto Ride",
                    "rating": 93,
                    "reason": "Frey rides. 108 speed rating gives him an outside chance at a price."
                }
            ],
            "danger_horse": null,
            "exotic_strategy": "Win Bet #3, Exacta Box 3-5, Trifecta 3,5 / 3,5,9 / 1,3,5,7,9"
        },
        {
            "number": 9,
            "distance": "1 Mile",
            "surface": "Turf",
            "confidence_level": "High",
            "selections": [
                {
                    "number": "9",
                    "barrier": "9",
                    "name": "Grand Slam Smile",
                    "rating": 112,
                    "reason": "Standout class (118) and speed (125). Outside draw shouldn't be an issue for this talented filly."
                },
                {
                    "number": "5",
                    "barrier": "5",
                    "name": "May Day Ready",
                    "rating": 108,
                    "reason": "Fresu rides for Mandella. 115 speed rating and 116 class makes her the primary threat."
                },
                {
                    "number": "2",
                    "barrier": "2",
                    "name": "Tirupati",
                    "rating": 105,
                    "reason": "Kimura rides for Thomas. 116 speed rating and drawn well inside."
                },
                {
                    "number": "7",
                    "barrier": "7",
                    "name": "Watchtower",
                    "rating": 102,
                    "reason": "Baltas trainee with Orantes. 118 speed rating puts her in the exotic picture."
                }
            ],
            "danger_horse": {
                "number": "8",
                "barrier": "8",
                "name": "Take A Breath (gb)",
                "rating": 100,
                "reason": "Jaramillo rides for Glatt. 110 speed rating and dangerous connections."
            },
            "exotic_strategy": "Win Bet #9, Exacta 9 / 2,5, Trifecta 9 / 2,5,7 / 2,5,7,8"
        }
    ]
}