{
    "meta": {
        "track": "Scone",
        "date": "2026-01-29",
        "track_condition": "Good 4"
    },
    "races": [
        {
            "number": 1,
            "confidence_level": "High (4.5 Stars)",
            "analysis_summary": "A field of first starters where trial form is king. Better By Far represents the elite Waterhouse/Bott stable and won a Randwick trial by nearly 3 lengths. This is a significant class edge over local country horses.",
            "picks": {
                "top_pick": {
                    "number": "3",
                    "name": "Better By Far",
                    "rating": 105,
                    "reason": "Waterhouse/Bott 2yo with dominant trial win at Randwick. 'Unexposed Elite' protocol applies."
                },
                "danger_horse": {
                    "number": "2",
                    "name": "Savage Look",
                    "rating": 96,
                    "reason": "Local trainer Rodney Northam has excellent strike rate with 2yos. Won trial well."
                },
                "value_bet": {
                    "number": "5",
                    "name": "Rubelin",
                    "odds": "$11.00",
                    "reason": "Drawn barrier 1 and won a trial at Dubbo. Could pinch a place at odds."
                },
                "fourth_pick": {
                    "number": "6",
                    "name": "Sambuca Sky"
                }
            },
            "exotic_strategy": {
                "exacta": "3 / 2, 5, 6",
                "trifecta": "3 / 2, 5, 6 / 2, 4, 5, 6",
                "rationale": "Keying #3 to win. It should be too fast and too professional for these."
            },
            "contenders": [
                {
                    "number": "3",
                    "name": "Better By Far",
                    "barrier": "7",
                    "weight": "123",
                    "rating": 105,
                    "probability": 45.0
                },
                {
                    "number": "2",
                    "name": "Savage Look",
                    "barrier": "3",
                    "weight": "128",
                    "rating": 96,
                    "probability": 20.0
                },
                {
                    "number": "5",
                    "name": "Rubelin",
                    "barrier": "1",
                    "weight": "123",
                    "rating": 92,
                    "probability": 12.0
                },
                {
                    "number": "6",
                    "name": "Sambuca Sky",
                    "barrier": "4",
                    "weight": "123",
                    "rating": 90,
                    "probability": 10.0
                }
            ]
        },
        {
            "number": 2,
            "confidence_level": "Medium (3 Stars)",
            "analysis_summary": "Southerly Buster drops significantly in grade from Metro/Provincial BM78/66 level to a Country BM66. Despite the weight, the class edge is distinct.",
            "picks": {
                "top_pick": {
                    "number": "2",
                    "name": "Southerly Buster",
                    "rating": 100,
                    "reason": "Class dropper. Last run in BM78 grade. Massive edge in this company."
                },
                "danger_horse": {
                    "number": "6",
                    "name": "Flaming Moon",
                    "rating": 97,
                    "reason": "Last start winner in BM58. Cummings stable. On an upward spiral."
                },
                "value_bet": {
                    "number": "7",
                    "name": "Spenzalot",
                    "odds": "$5.00",
                    "reason": "Consistent type who ran well at this distance range last start."
                },
                "fourth_pick": {
                    "number": "4",
                    "name": "She's Got Teeth"
                }
            },
            "exotic_strategy": {
                "exacta": "2, 6 / 2, 6, 7",
                "trifecta": "2, 6 / 2, 4, 6, 7 / 2, 4, 6, 7, 8",
                "rationale": "Box the top two class horses and cover the consistent #7."
            },
            "contenders": [
                {
                    "number": "2",
                    "name": "Southerly Buster",
                    "barrier": "9",
                    "weight": "133",
                    "rating": 100,
                    "probability": 30.0
                },
                {
                    "number": "6",
                    "name": "Flaming Moon",
                    "barrier": "1",
                    "weight": "128",
                    "rating": 97,
                    "probability": 25.0
                },
                {
                    "number": "7",
                    "name": "Spenzalot",
                    "barrier": "2",
                    "weight": "130",
                    "rating": 94,
                    "probability": 15.0
                },
                {
                    "number": "4",
                    "name": "She's Got Teeth",
                    "barrier": "5",
                    "weight": "129",
                    "rating": 92,
                    "probability": 12.0
                }
            ]
        },
        {
            "number": 3,
            "confidence_level": "High (4 Stars)",
            "analysis_summary": "Are You Kidding brings the lethal Messara/Bullock combination to a country maiden. Ran 2nd on debut and should improve sharply.",
            "picks": {
                "top_pick": {
                    "number": "3",
                    "name": "Are You Kidding",
                    "rating": 102,
                    "reason": "Messara/Bullock combination at Scone is striking at >30%. Strong debut 2nd."
                },
                "danger_horse": {
                    "number": "8",
                    "name": "Zo Frilling",
                    "rating": 95,
                    "reason": "Resuming with solid form references. Placed in stronger maidens previously."
                },
                "value_bet": {
                    "number": "6",
                    "name": "On One",
                    "odds": "$16.00",
                    "reason": "First starter from Cavanough yard who won a trial. Watch market."
                },
                "fourth_pick": {
                    "number": "12",
                    "name": "Silent Serenade"
                }
            },
            "exotic_strategy": {
                "exacta": "3 / 6, 8, 12",
                "trifecta": "3 / 6, 8, 12 / 1, 6, 8, 10, 12",
                "rationale": "Banker #3. The stable does not miss often in these races."
            },
            "contenders": [
                {
                    "number": "3",
                    "name": "Are You Kidding",
                    "barrier": "14",
                    "weight": "128",
                    "rating": 102,
                    "probability": 40.0
                },
                {
                    "number": "8",
                    "name": "Zo Frilling",
                    "barrier": "5",
                    "weight": "126",
                    "rating": 95,
                    "probability": 18.0
                },
                {
                    "number": "6",
                    "name": "On One",
                    "barrier": "6",
                    "weight": "127",
                    "rating": 90,
                    "probability": 10.0
                },
                {
                    "number": "12",
                    "name": "Silent Serenade",
                    "barrier": "1",
                    "weight": "122",
                    "rating": 88,
                    "probability": 8.0
                }
            ]
        },
        {
            "number": 4,
            "confidence_level": "Medium (3.5 Stars)",
            "analysis_summary": "St Faith's contested a Listed race on debut. Even finishing down the track, that class experience is superior to a country maiden field.",
            "picks": {
                "top_pick": {
                    "number": "5",
                    "name": "St Faith's",
                    "rating": 98,
                    "reason": "Debuted in the Listed Woodlands Stakes. Drops to a country maiden. Huge class edge."
                },
                "danger_horse": {
                    "number": "1",
                    "name": "Proclivity",
                    "rating": 96,
                    "reason": "Bullock rides. Placed at Newcastle previously. Strong contender."
                },
                "value_bet": {
                    "number": "11",
                    "name": "Straight South",
                    "odds": "$20.00",
                    "reason": "Improved 2nd last start. Getting closer."
                },
                "fourth_pick": {
                    "number": "8",
                    "name": "Perfect Force"
                }
            },
            "exotic_strategy": {
                "exacta": "1, 5 / 1, 5, 8, 11",
                "trifecta": "1, 5 / 1, 5, 8, 11 / 1, 5, 8, 11",
                "rationale": "Two horse race between the class runners #1 and #5."
            },
            "contenders": [
                {
                    "number": "5",
                    "name": "St Faith's",
                    "barrier": "11",
                    "weight": "122",
                    "rating": 98,
                    "probability": 35.0
                },
                {
                    "number": "1",
                    "name": "Proclivity",
                    "barrier": "8",
                    "weight": "130",
                    "rating": 96,
                    "probability": 30.0
                },
                {
                    "number": "11",
                    "name": "Straight South",
                    "barrier": "2",
                    "weight": "126",
                    "rating": 88,
                    "probability": 10.0
                },
                {
                    "number": "8",
                    "name": "Perfect Force",
                    "barrier": "5",
                    "weight": "123",
                    "rating": 87,
                    "probability": 8.0
                }
            ]
        },
        {
            "number": 5,
            "confidence_level": "Medium (3 Stars)",
            "analysis_summary": "Almonzo brings strong Newcastle form to Scone. The Lees/Bullock combination is formidable in this region.",
            "picks": {
                "top_pick": {
                    "number": "1",
                    "name": "Almonzo",
                    "rating": 99,
                    "reason": "Kris Lees & Aaron Bullock. Placed at Newcastle (Provincial) which is superior form."
                },
                "danger_horse": {
                    "number": "4",
                    "name": "Canadian Fling",
                    "rating": 97,
                    "reason": "Waterhouse/Bott runner. Placed at Gosford last start. Will be on pace."
                },
                "value_bet": {
                    "number": "5",
                    "name": "Master Zous",
                    "odds": "$3.50",
                    "reason": "Ran 2nd at Canterbury (Metro) two starts back. That form wins this."
                },
                "fourth_pick": {
                    "number": "10",
                    "name": "Savanna Golden Boy"
                }
            },
            "exotic_strategy": {
                "exacta": "Box 1, 4, 5",
                "trifecta": "1, 4, 5 / 1, 4, 5 / 1, 4, 5, 7, 10",
                "rationale": "Strong trio at the top. Box them."
            },
            "contenders": [
                {
                    "number": "1",
                    "name": "Almonzo",
                    "barrier": "6",
                    "weight": "130",
                    "rating": 99,
                    "probability": 28.0
                },
                {
                    "number": "4",
                    "name": "Canadian Fling",
                    "barrier": "11",
                    "weight": "128",
                    "rating": 97,
                    "probability": 25.0
                },
                {
                    "number": "5",
                    "name": "Master Zous",
                    "barrier": "8",
                    "weight": "128",
                    "rating": 96,
                    "probability": 22.0
                },
                {
                    "number": "10",
                    "name": "Savanna Golden Boy",
                    "barrier": "9",
                    "weight": "123",
                    "rating": 90,
                    "probability": 10.0
                }
            ]
        },
        {
            "number": 6,
            "confidence_level": "Low (2 Stars)",
            "analysis_summary": "Open race. Shutter drops from Class 3 to BM58 and maps well. Ghaznavi is consistent in this grade.",
            "picks": {
                "top_pick": {
                    "number": "3",
                    "name": "Shutter",
                    "rating": 94,
                    "reason": "Ran 4th in a Class 3 last start. Drops to BM58. Proven at track."
                },
                "danger_horse": {
                    "number": "5",
                    "name": "Ghaznavi",
                    "rating": 93,
                    "reason": "Runner-up in this grade last start. Consistent."
                },
                "value_bet": {
                    "number": "2",
                    "name": "Big Short",
                    "odds": "$10.00",
                    "reason": "Drops from BM66. Has won 3 times on Good tracks."
                },
                "fourth_pick": {
                    "number": "8",
                    "name": "Questionable"
                }
            },
            "exotic_strategy": {
                "exacta": "3, 5 / 2, 3, 5, 8",
                "trifecta": "3, 5 / 2, 3, 5, 8 / 2, 3, 4, 5, 8, 9",
                "rationale": "Wide open race. Go wide in exotics."
            },
            "contenders": [
                {
                    "number": "3",
                    "name": "Shutter",
                    "barrier": "10",
                    "weight": "132",
                    "rating": 94,
                    "probability": 22.0
                },
                {
                    "number": "5",
                    "name": "Ghaznavi",
                    "barrier": "5",
                    "weight": "131",
                    "rating": 93,
                    "probability": 20.0
                },
                {
                    "number": "2",
                    "name": "Big Short",
                    "barrier": "2",
                    "weight": "133",
                    "rating": 91,
                    "probability": 15.0
                },
                {
                    "number": "8",
                    "name": "Questionable",
                    "barrier": "1",
                    "weight": "126",
                    "rating": 90,
                    "probability": 12.0
                }
            ]
        },
        {
            "number": 7,
            "confidence_level": "Medium (3 Stars)",
            "analysis_summary": "Vierville resumes with a big weight but brings superior class (Metro/Provincial form). Quick Sharp is a last start winner in this grade.",
            "picks": {
                "top_pick": {
                    "number": "2",
                    "name": "Vierville",
                    "rating": 98,
                    "reason": "Resuming. Has won fresh before. Class above these despite the 62.5kg (after claim)."
                },
                "danger_horse": {
                    "number": "5",
                    "name": "Quick Sharp",
                    "rating": 96,
                    "reason": "Last start winner in this grade. Northam stable flying."
                },
                "value_bet": {
                    "number": "4",
                    "name": "Mirai San",
                    "odds": "$4.50",
                    "reason": "Consistent. Placed last two. Maps well."
                },
                "fourth_pick": {
                    "number": "1",
                    "name": "Iknowyou"
                }
            },
            "exotic_strategy": {
                "exacta": "2, 5 / 1, 2, 4, 5",
                "trifecta": "2, 5 / 1, 2, 4, 5 / 1, 2, 4, 5, 6",
                "rationale": "Class runners to the fore."
            },
            "contenders": [
                {
                    "number": "2",
                    "name": "Vierville",
                    "barrier": "2",
                    "weight": "137",
                    "rating": 98,
                    "probability": 28.0
                },
                {
                    "number": "5",
                    "name": "Quick Sharp",
                    "barrier": "1",
                    "weight": "134",
                    "rating": 96,
                    "probability": 25.0
                },
                {
                    "number": "4",
                    "name": "Mirai San",
                    "barrier": "11",
                    "weight": "134",
                    "rating": 94,
                    "probability": 18.0
                },
                {
                    "number": "1",
                    "name": "Iknowyou",
                    "barrier": "6",
                    "weight": "137",
                    "rating": 92,
                    "probability": 12.0
                }
            ]
        },
        {
            "number": 8,
            "confidence_level": "Medium (3 Stars)",
            "analysis_summary": "Beyond My Ken was narrowly beaten carrying big weight last start. Super Freds drops massively in class from BM74 to BM58.",
            "picks": {
                "top_pick": {
                    "number": "1",
                    "name": "Beyond My Ken",
                    "rating": 97,
                    "reason": "Carried 138lbs (62.5kg) last start and missed by a nose. Tough horse."
                },
                "danger_horse": {
                    "number": "3",
                    "name": "Super Freds",
                    "rating": 96,
                    "reason": "Drops from BM74/68 grade. This is a huge class drop to BM58."
                },
                "value_bet": {
                    "number": "6",
                    "name": "Bent As Hell",
                    "odds": "$20.00",
                    "reason": "Resuming. Has ability and draws well."
                },
                "fourth_pick": {
                    "number": "2",
                    "name": "Ran Na Lady"
                }
            },
            "exotic_strategy": {
                "exacta": "1, 3 / 1, 2, 3, 6",
                "trifecta": "1, 3 / 1, 2, 3, 6 / 1, 2, 3, 6, 7",
                "rationale": "Top two have a clear ratings edge."
            },
            "contenders": [
                {
                    "number": "1",
                    "name": "Beyond My Ken",
                    "barrier": "8",
                    "weight": "140",
                    "rating": 97,
                    "probability": 30.0
                },
                {
                    "number": "3",
                    "name": "Super Freds",
                    "barrier": "1",
                    "weight": "137",
                    "rating": 96,
                    "probability": 28.0
                },
                {
                    "number": "6",
                    "name": "Bent As Hell",
                    "barrier": "4",
                    "weight": "132",
                    "rating": 90,
                    "probability": 12.0
                },
                {
                    "number": "2",
                    "name": "Ran Na Lady",
                    "barrier": "12",
                    "weight": "140",
                    "rating": 89,
                    "probability": 10.0
                }
            ]
        }
    ]
}