{
    "meta": {
        "track": "Turf_Paradise",
        "date": "2026-01-29",
        "track_condition": "Fast"
    },
    "races": [
        {
            "number": 1,
            "distance": "350 Yards",
            "surface": "Dirt",
            "confidence_level": "High",
            "selections": [
                {
                    "number": "6",
                    "barrier": "6",
                    "name": "Fast Captain Shana",
                    "reason": "Dominant recent speed figure (77) compared to field average. Just missed by a neck last out; clear standout on paper."
                },
                {
                    "number": "5",
                    "barrier": "5",
                    "name": "Fancy Seis",
                    "reason": "Consistent speed figures (62, 61) and should be in the mix for the placings."
                },
                {
                    "number": "1",
                    "barrier": "1",
                    "name": "Jess Rock It",
                    "reason": "Showed improvement last start with a 51 speed index; rail draw helps in QH sprints."
                },
                {
                    "number": "2",
                    "barrier": "2",
                    "name": "Daddys A Cartel",
                    "reason": "First time starter from a barn that can pop; watch the tote."
                }
            ],
            "danger_horse": null,
            "exotic_strategy": {
                "strategy": "Win Bet #6; Exacta 6 over 1,5"
            }
        },
        {
            "number": 2,
            "distance": "350 Yards",
            "surface": "Dirt",
            "confidence_level": "Medium",
            "selections": [
                {
                    "number": "4",
                    "barrier": "4",
                    "name": "Hiclass Famous One",
                    "reason": "Posted a strong 71 speed index recently (Dec 22), which is superior to this field's recent form."
                },
                {
                    "number": "8",
                    "barrier": "8",
                    "name": "Kams Cartel",
                    "reason": "Ran a respectable 62 speed index in debut; improvement expected."
                },
                {
                    "number": "7",
                    "barrier": "7",
                    "name": "Sign Fire",
                    "reason": "Speed figure of 60 fits well here; solid exotic contender."
                },
                {
                    "number": "3",
                    "barrier": "3",
                    "name": "Myka Roon Csj",
                    "reason": "Speed figure of 54 puts her in the mix for lower rungs of the exotics."
                }
            ],
            "danger_horse": {
                "number": "8",
                "barrier": "8",
                "name": "Kams Cartel",
                "reason": "Lightly raced with room to improve past the top pick."
            },
            "exotic_strategy": {
                "strategy": "Exacta Box 4-8; Trifecta 4,8 / 4,7,8 / 3,4,7,8"
            }
        },
        {
            "number": 3,
            "distance": "4 1/2 Furlongs",
            "surface": "Dirt",
            "confidence_level": "High",
            "selections": [
                {
                    "number": "1",
                    "barrier": "1",
                    "name": "She's A One Of One",
                    "reason": "Significant class drop from CLM8500 to CLM4500. Speed figure of 62 two back dominates this group."
                },
                {
                    "number": "6",
                    "barrier": "6",
                    "name": "Lightsoutscarlett",
                    "reason": "Consistent runner with a recent 57 speed figure; logical alternative if the favorite falters."
                },
                {
                    "number": "8",
                    "barrier": "8",
                    "name": "Behindthebar",
                    "reason": "Has back class and a speed figure of 59, but form has been spotty recently."
                },
                {
                    "number": "3",
                    "barrier": "3",
                    "name": "Beyond The Law",
                    "reason": "Speed figures in the 40s make her a fringe player for the superfecta."
                }
            ],
            "danger_horse": {
                "number": "6",
                "barrier": "6",
                "name": "Lightsoutscarlett",
                "reason": "Consistent type who could pick up the pieces if the dropper (#1) isn't ready."
            },
            "exotic_strategy": {
                "strategy": "Win #1; Exacta 1 / 6,8"
            }
        },
        {
            "number": 4,
            "distance": "6 1/2 Furlongs",
            "surface": "Dirt",
            "confidence_level": "High",
            "selections": [
                {
                    "number": "7",
                    "barrier": "7",
                    "name": "Rocky Bay Rae",
                    "reason": "Last-out speed figure of 91 is a standout. Drops from AOC20000 where she finished 2nd."
                },
                {
                    "number": "3",
                    "barrier": "3",
                    "name": "Ima Margarita Girl",
                    "reason": "Cutting back to a sprint after an 87 speed figure routing. Dangerous closer."
                },
                {
                    "number": "1",
                    "barrier": "1",
                    "name": "Blue Spirit",
                    "reason": "Consistent mid-70s to low-80s speed figures. Solid underneath play."
                },
                {
                    "number": "4",
                    "barrier": "4",
                    "name": "Bubbles Up",
                    "reason": "Coming off a win with a 74 speed figure; steps up in class but in good form."
                }
            ],
            "danger_horse": {
                "number": "3",
                "barrier": "3",
                "name": "Ima Margarita Girl",
                "reason": "High class router cutting back; if the pace is hot, she wins."
            },
            "exotic_strategy": {
                "strategy": "Trifecta Key 7 / 1,3,4"
            }
        },
        {
            "number": 5,
            "distance": "4 1/2 Furlongs",
            "surface": "Dirt",
            "confidence_level": "Medium",
            "selections": [
                {
                    "number": "1",
                    "barrier": "1",
                    "name": "Pakas Secret",
                    "reason": "Recent 67 speed figure on Jan 7 is the best current form in a weak field. Finished 3rd ahead of rival #6."
                },
                {
                    "number": "6",
                    "barrier": "6",
                    "name": "Bear Encounter",
                    "reason": "Ran a 58 in the same race as the top pick; logical second choice."
                },
                {
                    "number": "5",
                    "barrier": "5",
                    "name": "Tomorrownevercomes",
                    "reason": "Recent 55 speed figure puts him in the mix for the exotics."
                },
                {
                    "number": "7",
                    "barrier": "7",
                    "name": "Levi Gone Wild",
                    "reason": "Speed figure of 53 is competitive for the minor awards."
                }
            ],
            "danger_horse": null,
            "exotic_strategy": {
                "strategy": "Win #1; Exacta 1 / 5,6"
            }
        },
        {
            "number": 6,
            "distance": "4 1/2 Furlongs",
            "surface": "Dirt",
            "confidence_level": "Medium",
            "selections": [
                {
                    "number": "7",
                    "barrier": "7",
                    "name": "Ginger In Charge",
                    "reason": "Top last-out speed figure of 76 (Jan 7). Finished 2nd and looks ready to win."
                },
                {
                    "number": "3",
                    "barrier": "3",
                    "name": "Cocktail Princess",
                    "reason": "Ran a 73 speed figure on Jan 6; clearly the main danger to the top pick."
                },
                {
                    "number": "8",
                    "barrier": "8",
                    "name": "Song Of Shadows",
                    "reason": "Also ran a 73 recently (Jan 19) but finished 4th; solid contender."
                },
                {
                    "number": "2",
                    "barrier": "2",
                    "name": "Pleasingly",
                    "reason": "Speed figure of 64 is a step below the top three but best of the rest."
                }
            ],
            "danger_horse": {
                "number": "3",
                "barrier": "3",
                "name": "Cocktail Princess",
                "reason": "Very close on speed figures (73 vs 76); could easily turn the tables."
            },
            "exotic_strategy": {
                "strategy": "Exacta Box 3-7; Trifecta 3,7 / 3,7,8 / 2,3,7,8"
            }
        },
        {
            "number": 7,
            "distance": "6 1/2 Furlongs",
            "surface": "Dirt",
            "confidence_level": "Medium",
            "selections": [
                {
                    "number": "5",
                    "barrier": "5",
                    "name": "Let Me Help You",
                    "reason": "Highest recent speed figure (81) on Jan 8. Value play at 6/1."
                },
                {
                    "number": "7",
                    "barrier": "7",
                    "name": "Moonlight Road",
                    "reason": "Consistent runner with a 79 speed figure last out; finished 2nd."
                },
                {
                    "number": "4",
                    "barrier": "4",
                    "name": "K R Rules",
                    "reason": "Proven dirt form (78 speed in Dec); threat despite recent turf run."
                },
                {
                    "number": "2",
                    "barrier": "2",
                    "name": "Jimmy's Wild Boy",
                    "reason": "Speed figure of 68 is competitive for the bottom of the exotics."
                }
            ],
            "danger_horse": {
                "number": "7",
                "barrier": "7",
                "name": "Moonlight Road",
                "reason": "Very consistent and only 2 points off the top pick's speed figure."
            },
            "exotic_strategy": {
                "strategy": "Win #5; Exacta Box 5-7-4"
            }
        },
        {
            "number": 8,
            "distance": "4 1/2 Furlongs",
            "surface": "Dirt",
            "confidence_level": "Medium",
            "selections": [
                {
                    "number": "4",
                    "barrier": "4",
                    "name": "Crystal Proof",
                    "reason": "Most reliable recent form with a 69 speed figure (3rd place finish)."
                },
                {
                    "number": "3",
                    "barrier": "3",
                    "name": "Happy Chappy",
                    "reason": "Ran a 68 in the same race as the top pick; very little separates them."
                },
                {
                    "number": "6",
                    "barrier": "6",
                    "name": "Capital Heat",
                    "reason": "Had a legitimate excuse last time (lost iron/rider issues); capable of 71 speed."
                },
                {
                    "number": "9",
                    "barrier": "9",
                    "name": "Hot Jammies",
                    "reason": "Recent 62 speed figure puts her in the hunt for a minor share."
                }
            ],
            "danger_horse": {
                "number": "6",
                "barrier": "6",
                "name": "Capital Heat",
                "reason": "Forgive the last run; previous form (71 speed) wins this race."
            },
            "exotic_strategy": {
                "strategy": "Trifecta Box 3-4-6"
            }
        }
    ]
}